README.rst
setup.py
GitAgent.egg-info/PKG-INFO
GitAgent.egg-info/SOURCES.txt
GitAgent.egg-info/dependency_links.txt
GitAgent.egg-info/requires.txt
GitAgent.egg-info/top_level.txt
gitagent/__init__.py
gitagent/__main__.py
gitagent/agent.py
gitagent/auth.py
gitagent/client.py