Metadata-Version: 1.1
Name: GitAgent
Version: 0.0.16
Summary: A web server receive HTTP request to pull local repository
Home-page: https://github.com/alexazhou/GitAgent
Author: AlexaZhou
Author-email: AlexaZhou@163.com
License: LGPL
Keywords: git pull hook
Platform: UNKNOWN
Classifier: Development Status :: 3 - Alpha
Classifier: Intended Audience :: Developers
Classifier: Topic :: Software Development :: Build Tools
Classifier: License :: OSI Approved :: GNU Lesser General Public License v3 or later (LGPLv3+)
Classifier: Programming Language :: Python :: 3
Classifier: Programming Language :: Python :: 3.3
Classifier: Programming Language :: Python :: 3.4
Classifier: Programming Language :: Python :: 3.5
